Workbook

Sheet Questionnaire
A1: QCM — Formation assurance vie
A2: 20 questions · 5 par module · une seule bonne réponse par question · 1 point par bonne réponse
A4: N° | B4: Module | C4: Question | D4: A | E4: B | F4: C | G4: D | H4: Réponse
A5: 1 | B5: 2 · Cadre légal et réglementaire | C5: Le Code des assurances tunisien a été promulgué par : | D5: La loi n° 92-24 du 9 mars 1992 | E5: La loi n° 85-12 du 5 mars 1985 | F5: Le décret n° 2003-1098 | G5: Le règlement CGA 01/2016
A6: 2 | B6: 2 · Cadre légal et réglementaire | C6: Quel est le délai maximal de renonciation au contrat d'assurance vie ? | D6: 8 jours | E6: 15 jours | F6: 30 jours | G6: 2 mois
A7: 3 | B7: 2 · Cadre légal et réglementaire | C7: Si une demande de rachat intervient pendant les 5 premières années du contrat, la pénalité de rachat appliquée par l'assureur : | D7: Est interdite | E7: Ne doit pas dépasser 5 % du montant racheté | F7: Ne doit pas dépasser 10 % du montant racheté | G7: Est librement fixée par l'assureur
A8: 4 | B8: 2 · Cadre légal et réglementaire | C8: Concernant l'avance sur contrat (règlement 1/2016 et son avenant), quelle affirmation est EXACTE ? | D8: Le taux d'intérêt ne doit pas dépasser TMM + 3 % | E8: L'avance peut atteindre 100 % de l'épargne constituée | F8: Le contrat doit avoir au moins 5 ans d'ancienneté | G8: La période de remboursement peut être renouvelée sans limite
A9: 5 | B9: 2 · Cadre légal et réglementaire | C9: Le transfert d'un contrat doit être exécuté dans un délai maximum de : | D9: 1 mois pour un contrat individuel, 3 mois pour l'ensemble des adhésions à un contrat collectif | E9: 3 mois pour un contrat individuel, 1 mois pour l'ensemble des adhésions | F9: 1 mois dans tous les cas | G9: 3 mois dans tous les cas
A10: 6 | B10: 3 · Caractéristiques du contrat | C10: En assurance vie, les sommes assurées sont : | D10: Plafonnées par la valeur du préjudice subi | E10: Fixées librement par les parties au contrat | F10: Fixées par le CGA | G10: Limitées à 100 000 dinars
A11: 7 | B11: 3 · Caractéristiques du contrat | C11: Après paiement de la somme assurée, l'assureur-vie peut-il se retourner contre le tiers responsable du sinistre ? | D11: Oui, au titre de la subrogation | E11: Oui, mais seulement si le contrat le prévoit | F11: Non, aucune subrogation n'est possible | G11: Non, sauf en cas de faute intentionnelle du tiers
A12: 8 | B12: 3 · Caractéristiques du contrat | C12: Le principe indemnitaire de l'article 16 CAT s'applique : | D12: À toutes les assurances | E12: Aux seules assurances de personnes | F12: Aux seuls contrats collectifs | G12: Aux seules assurances de dommages
A13: 9 | B13: 3 · Caractéristiques du contrat | C13: En cas de suicide volontaire de l'assuré, l'assureur : | D13: Ne verse rien aux ayants droit | E13: Verse l'intégralité du capital assuré | F13: Verse une somme égale au montant de la provision mathématique | G13: Verse 50 % du capital assuré
A14: 10 | B14: 3 · Caractéristiques du contrat | C14: La faculté de rachat est obligatoire à la demande du contractant, SAUF pour : | D14: Les contrats vie entière | E14: Les contrats mixtes | F14: Les contrats de capitalisation | G14: Les temporaires en cas de décès
A15: 11 | B15: 4 · Les contrats d'assurance vie | C15: Dans un contrat de capital différé SANS contre-assurance, que se passe-t-il si l'assuré décède avant la date d'expiration ? | D15: Le capital est versé au bénéficiaire désigné | E15: Aucune prestation n'est versée | F15: Les primes sont remboursées avec intérêts | G15: La provision mathématique est versée
A16: 12 | B16: 4 · Les contrats d'assurance vie | C16: Dans une assurance combinée 100.25, la garantie en cas de vie représente : | D16: 25 % de la garantie décès | E16: 100 % de la garantie décès | F16: 50 % de la garantie décès | G16: 25 % des primes versées
... A24: 20 | B24: 5 · La fiscalité de l'assurance vie | C24: Pour les contrats collectifs Épargne dont le terme correspond à l'âge de départ à la retraite, le minimum de prime à la charge de l'employé est de : | D24: 1 % | E24: 5 % | F24: 10 % | G24: 20 %
A26: Colonne « Réponse » : saisir A, B, C ou D (liste déroulante). Source : support de formation Finasure « Présentation formation — assurance vie » (166 diapositives). Modules 1 « Le marché de l'assurance vie en Tunisie » et 6 « Les produits d'assurance sur le marché » volontairement exclus de l'évaluation.

Sheet Corrigé
A1: Corrigé formateur
A2: Réservé au formateur — à ne pas distribuer avec le questionnaire
A4: N° | B4: Module | C4: Question | D4: Bonne réponse | E4: Libellé de la bonne réponse | F4: Justification / référence
A5: 1 | B5: 2 · Cadre légal et réglementaire | C5: Le Code des assurances tunisien a été promulgué par : | D5: A | E5: La loi n° 92-24 du 9 mars 1992 | F5: Loi n° 92-24 du 9 mars 1992, parue au JORT n° 17 du 17 mars 1992, page 314.
A6: 2 | B6: 2 · Cadre légal et réglementaire | C6: Quel est le délai maximal de renonciation au contrat d'assurance vie ? | D6: B | E6: 15 jours | F6: Le souscripteur peut renoncer dans un délai fixé par le contrat, sans que celui-ci dépasse 15 jours. Toute la prime est alors remboursée.
A7: 3 | B7: 2 · Cadre légal et réglementaire | C7: Si une demande de rachat intervient pendant les 5 premières années du contrat, la pénalité de rachat appliquée par l'assureur : | D7: B | E7: Ne doit pas dépasser 5 % du montant racheté | F7: Pénalité plafonnée à 5 % du montant racheté. Pour les contrats en UC, aucune pénalité n'est appliquée quelle que soit l'ancienneté.
A8: 4 | B8: 2 · Cadre légal et réglementaire | C8: Concernant l'avance sur contrat (règlement 1/2016 et son avenant), quelle affirmation est EXACTE ? | D8: A | E8: Le taux d'intérêt ne doit pas dépasser TMM + 3 % | F8: Taux plafonné à TMM + 3 %. L'avance ne peut dépasser 80 % de l'épargne constituée, le contrat doit avoir au moins 2 ans d'ancienneté et le remboursement ne peut dépasser 36 mois non renouvelables.
A9: 5 | B9: 2 · Cadre légal et réglementaire | C9: Le transfert d'un contrat doit être exécuté dans un délai maximum de : | D9: A | E9: 1 mois pour un contrat individuel, 3 mois pour l'ensemble des adhésions à un contrat collectif | F9: 1 mois pour un contrat individuel ou une adhésion à un contrat collectif ; 3 mois pour l'ensemble des adhésions à un contrat collectif.
A10: 6 | B10: 3 · Caractéristiques du contrat | C10: En assurance vie, les sommes assurées sont : | D10: B | E10: Fixées librement par les parties au contrat | F10: Article 34 CAT : « les sommes assurées sont fixées par les parties au contrat ». C'est le principe forfaitaire — aucune valeur de référence ne vient plafonner le capital garanti.
A11: 7 | B11: 3 · Caractéristiques du contrat | C11: Après paiement de la somme assurée, l'assureur-vie peut-il se retourner contre le tiers responsable du sinistre ? | D11: C | E11: Non, aucune subrogation n'est possible | F11: Article 35 CAT : dans les assurances de personnes, l'assureur ne peut être subrogé aux droits du contractant ou du bénéficiaire contre des tiers. Les bénéficiaires cumulent donc le capital ET l'indemnisation due par le responsable.
A12: 8 | B12: 3 · Caractéristiques du contrat | C12: Le principe indemnitaire de l'article 16 CAT s'applique : | D12: D | E12: Aux seules assurances de dommages | F12: L'article 16 plafonne l'indemnité à la valeur de la chose assurée : il suppose un préjudice mesurable, ce qui n'existe pas en assurance de personnes. C'est le principe forfaitaire qui y prévaut.
A13: 9 | B13: 3 · Caractéristiques du contrat | C13: En cas de suicide volontaire de l'assuré, l'assureur : | D13: C | E13: Verse une somme égale au montant de la provision mathématique | F13: Article 37 CAT : l'assurance en cas de décès est sans effet en cas de suicide volontaire, mais l'assureur doit verser une somme égale à la provision mathématique. Le suicide inconscient donne lieu au versement intégral.
A14: 10 | B14: 3 · Caractéristiques du contrat | C14: La faculté de rachat est obligatoire à la demande du contractant, SAUF pour : | D14: D | E14: Les temporaires en cas de décès | F14: Article 42 CAT : les assurances temporaires en cas de décès ne donnent lieu ni à la réduction du capital ni au rachat du contrat (pure prévoyance).
A15: 11 | B15: 4 · Les contrats d'assurance vie | C15: Dans un contrat de capital différé SANS contre-assurance, que se passe-t-il si l'assuré décède avant la date d'expiration ? | D15: B | E15: Aucune prestation n'est versée | F15: Sans contre-assurance, le décès avant l'expiration ne donne lieu à aucune prestation. Avec contre-assurance : remboursement des primes, des primes + intérêts techniques, ou règlement de la PM.
A16: 12 | B16: 4 · Les contrats d'assurance vie | C16: Dans une assurance combinée 100.25, la garantie en cas de vie représente : | D16: A | E16: 25 % de la garantie décès | F16: La combinée 100.25 est une mixte à garanties inégales : la garantie vie est égale à 25 % de la garantie décès. C'est la combinaison la plus usitée.
... A24: 20 | B24: 5 · La fiscalité de l'assurance vie | C24: Pour les contrats collectifs Épargne dont le terme correspond à l'âge de départ à la retraite, le minimum de prime à la charge de l'employé est de : | D24: C | E24: 10 % | F24: 10 % pour les contrats collectifs Épargne dont le terme correspond à l'âge de départ à la retraite ; 5 % pour les autres contrats collectifs Épargne ; 1 % pour les contrats collectifs de prévoyance.

Sheet Notation
A1: Grille de notation
A2: Se remplit automatiquement à partir des onglets « Questionnaire » et « Corrigé »
A4: N° | B4: Module | C4: Réponse du candidat | D4: Bonne réponse | E4: Point obtenu
A5: 1 | B5: =Questionnaire!B5 -> 2 · Cadre légal et réglementaire | C5: =Questionnaire!H5 -> 0 | D5: =Corrigé!D5 -> A | E5: =IF(C5="",0,IF(UPPER(C5)=D5,1,0)) -> 0
A6: 2 | B6: =Questionnaire!B6 -> 2 · Cadre légal et réglementaire | C6: =Questionnaire!H6 -> 0 | D6: =Corrigé!D6 -> B | E6: =IF(C6="",0,IF(UPPER(C6)=D6,1,0)) -> 0
A7: 3 | B7: =Questionnaire!B7 -> 2 · Cadre légal et réglementaire | C7: =Questionnaire!H7 -> 0 | D7: =Corrigé!D7 -> B | E7: =IF(C7="",0,IF(UPPER(C7)=D7,1,0)) -> 0
A8: 4 | B8: =Questionnaire!B8 -> 2 · Cadre légal et réglementaire | C8: =Questionnaire!H8 -> 0 | D8: =Corrigé!D8 -> A | E8: =IF(C8="",0,IF(UPPER(C8)=D8,1,0)) -> 0
A9: 5 | B9: =Questionnaire!B9 -> 2 · Cadre légal et réglementaire | C9: =Questionnaire!H9 -> 0 | D9: =Corrigé!D9 -> A | E9: =IF(C9="",0,IF(UPPER(C9)=D9,1,0)) -> 0
A10: 6 | B10: =Questionnaire!B10 -> 3 · Caractéristiques du contrat | C10: =Questionnaire!H10 -> 0 | D10: =Corrigé!D10 -> B | E10: =IF(C10="",0,IF(UPPER(C10)=D10,1,0)) -> 0
A11: 7 | B11: =Questionnaire!B11 -> 3 · Caractéristiques du contrat | C11: =Questionnaire!H11 -> 0 | D11: =Corrigé!D11 -> C | E11: =IF(C11="",0,IF(UPPER(C11)=D11,1,0)) -> 0
A12: 8 | B12: =Questionnaire!B12 -> 3 · Caractéristiques du contrat | C12: =Questionnaire!H12 -> 0 | D12: =Corrigé!D12 -> D | E12: =IF(C12="",0,IF(UPPER(C12)=D12,1,0)) -> 0
A13: 9 | B13: =Questionnaire!B13 -> 3 · Caractéristiques du contrat | C13: =Questionnaire!H13 -> 0 | D13: =Corrigé!D13 -> C | E13: =IF(C13="",0,IF(UPPER(C13)=D13,1,0)) -> 0
A14: 10 | B14: =Questionnaire!B14 -> 3 · Caractéristiques du contrat | C14: =Questionnaire!H14 -> 0 | D14: =Corrigé!D14 -> D | E14: =IF(C14="",0,IF(UPPER(C14)=D14,1,0)) -> 0
A15: 11 | B15: =Questionnaire!B15 -> 4 · Les contrats d'assurance vie | C15: =Questionnaire!H15 -> 0 | D15: =Corrigé!D15 -> B | E15: =IF(C15="",0,IF(UPPER(C15)=D15,1,0)) -> 0
A16: 12 | B16: =Questionnaire!B16 -> 4 · Les contrats d'assurance vie | C16: =Questionnaire!H16 -> 0 | D16: =Corrigé!D16 -> A | E16: =IF(C16="",0,IF(UPPER(C16)=D16,1,0)) -> 0
... A24: 20 | B24: =Questionnaire!B24 -> 5 · La fiscalité de l'assurance vie | C24: =Questionnaire!H24 -> 0 | D24: =Corrigé!D24 -> C | E24: =IF(C24="",0,IF(UPPER(C24)=D24,1,0)) -> 0
D26: TOTAL / 20 | E26: =SUM(E5:E24) -> 0
D27: Note sur 20 | E27: =E26 -> 0
D28: Pourcentage | E28: =E27/20 -> 0
D29: Résultat | E29: =IF(E28>=0.7,"ACQUIS",IF(E28>=0.5,"À CONSOLIDER","NON ACQUIS")) -> NON ACQUIS
A31: Score par module
A32: Module | B32: Score | C32: Sur
A33: 2 · Cadre légal et réglementaire | B33: =SUMIFS($E$5:$E$24,$B$5:$B$24,A33) -> 0 | C33: 5
A34: 3 · Caractéristiques du contrat | B34: =SUMIFS($E$5:$E$24,$B$5:$B$24,A34) -> 0 | C34: 5
A35: 4 · Les contrats d'assurance vie | B35: =SUMIFS($E$5:$E$24,$B$5:$B$24,A35) -> 0 | C35: 5
A36: 5 · La fiscalité de l'assurance vie | B36: =SUMIFS($E$5:$E$24,$B$5:$B$24,A36) -> 0 | C36: 5
A39: Barème : 1 point par bonne réponse, 0 sinon (pas de point négatif). Seuils proposés : ACQUIS ≥ 70 %, À CONSOLIDER ≥ 50 %, sinon NON ACQUIS — à ajuster selon votre politique de formation. Source : support de formation Finasure « Présentation formation — assurance vie » (166 diapositives). Modules 1 « Le marché de l'assurance vie en Tunisie » et 6 « Les produits d'assurance sur le marché » volontairement exclus de l'évaluation.
